	{
    "race": "MEN",
    "type": "STRONGHOLD",

    "attributes": {
        "resistance": 3,
        "wounds": 1,
        "capacity": 0,
        "timeToBuild": 60,
        "repairSpeed": 0.2,
        "sightRange": 60
    },

    "resources": {
        "wood": 150,
        "metal": 100,
        "food": 0
    },

	"abilities":[
		{
			"name":"Create Farm"
		},

		{
			"name":"Create Mine"
		},

		{
			"name":"Create Sawmill"
		},

        {
            "name":"Create Archery"
        },

        {
            "name":"Create Stable"
        },

        {
            "name": "Sell"
        }
	]
}
